LICENSE
README.md
setup.py
puren_tonbo/__init__.py
puren_tonbo/__main__.py
puren_tonbo/_version.py
puren_tonbo/mzipaes.py
puren_tonbo/ui.py
puren_tonbo/vimdecrypt.py
puren_tonbo.egg-info/PKG-INFO
puren_tonbo.egg-info/SOURCES.txt
puren_tonbo.egg-info/dependency_links.txt
puren_tonbo.egg-info/entry_points.txt
puren_tonbo.egg-info/requires.txt
puren_tonbo.egg-info/top_level.txt
puren_tonbo/resources/icon512x512.png
puren_tonbo/resources/puren_tonbo_32x31.ico
puren_tonbo/resources/puren_tonbo_red_icon_32x32.ico
puren_tonbo/resources/red_icon512x498_4colors.png
puren_tonbo/tests/__init__.py
puren_tonbo/tests/__main__.py
puren_tonbo/tests/generate_data.py
puren_tonbo/tests/testsuite.py
puren_tonbo/tests/data/README.md
puren_tonbo/tests/data/aesop.chi
puren_tonbo/tests/data/aesop.txt
puren_tonbo/tests/data/aesop_linux.openssl_aes256cbc_pbkdf2_10k
puren_tonbo/tests/data/aesop_linux.vimcrypt1
puren_tonbo/tests/data/aesop_linux.vimcrypt2
puren_tonbo/tests/data/aesop_linux.vimcrypt3
puren_tonbo/tests/data/aesop_linux_7z.aes256.zip
puren_tonbo/tests/data/aesop_linux_7z.aes256stored.zip
puren_tonbo/tests/data/aesop_linux_7z.old.zip
puren_tonbo/tests/data/aesop_linux_7z.oldstored.zip
puren_tonbo/tests/data/aesop_win.openssl_aes256cbc_pbkdf2_10k
puren_tonbo/tests/data/aesop_win.vimcrypt1
puren_tonbo/tests/data/aesop_win.vimcrypt2
puren_tonbo/tests/data/aesop_win.vimcrypt3
puren_tonbo/tests/data/aesop_win_7z.aes256.zip
puren_tonbo/tests/data/aesop_win_7z.aes256stored.zip
puren_tonbo/tests/data/aesop_win_7z.old.zip
puren_tonbo/tests/data/aesop_win_7z.oldstored.zip
puren_tonbo/tests/data/aesop_win_ccrypt.cpt
puren_tonbo/tests/data/aesop_win_encryptpad.asc
puren_tonbo/tests/data/aesop_win_encryptpad.gpg
puren_tonbo/tests/data/aesop_win_winrar.aes256.zip
puren_tonbo/tests/data/aesop_win_winrar.aes256stored.zip
puren_tonbo/tests/data/latin.txt
puren_tonbo/tests/data/pg28_the_fables_of_aesop_utf8.chi
puren_tonbo/tests/data/pg28_the_fables_of_aesop_utf8.txt
puren_tonbo/tests/data/utf8_latin.txt
puren_tonbo/tools/__init__.py
puren_tonbo/tools/ptcat.py
puren_tonbo/tools/ptcipher.py
puren_tonbo/tools/ptconfig.py
puren_tonbo/tools/ptgrep.py
puren_tonbo/tools/ptig.py
puren_tonbo/tools/ptpyvim.py
