Metadata-Version: 2.1
Name: puren_tonbo
Version: 0.0.0.dev3
Summary: Plain text notes Tombo (chi) alternative, also supports AES-256 ZIP AE-1/AE-2 and VimCrypt encrypted files. Work-In-Progress (WIP)!
Home-page: https://github.com/clach04/puren_tonbo
Author: clach04
Platform: any
Classifier: Development Status :: 4 - Beta
Classifier: License :: OSI Approved :: GNU Lesser General Public License v2 (LGPLv2)
Classifier: Operating System :: OS Independent
Classifier: Topic :: Security :: Cryptography
Classifier: Topic :: Text Processing :: General
Classifier: Programming Language :: Python
Classifier: Programming Language :: Python :: 2
Classifier: Programming Language :: Python :: 2.7
Classifier: Programming Language :: Python :: 3
Classifier: Programming Language :: Python :: 3.5
Classifier: Programming Language :: Python :: 3.6
Classifier: Programming Language :: Python :: 3.10
Classifier: Programming Language :: Python :: 3.11
Classifier: Programming Language :: Python :: 3.12
License-File: LICENSE
Requires-Dist: colorama
Requires-Dist: pycryptodome
Requires-Dist: python-gnupg
Requires-Dist: openssl_enc_compat
Requires-Dist: pyzipper
Requires-Dist: pywin32
Provides-Extra: chi-io
Requires-Dist: chi_io; extra == "chi-io"
